fb_friend_list_scraper/__init__.py
fb_friend_list_scraper/scraper.py
fb_friend_list_scraper-0.3.6.dist-info/LICENSE
fb_friend_list_scraper-0.3.6.dist-info/METADATA
fb_friend_list_scraper-0.3.6.dist-info/WHEEL
fb_friend_list_scraper-0.3.6.dist-info/entry_points.txt
fb_friend_list_scraper-0.3.6.dist-info/top_level.txt
fb_friend_list_scraper-0.3.6.dist-info/RECORD
