Metadata-Version: 2.1
Name: fb-friend-list-scraper
Version: 0.3.6
Summary: Tool to scrape names and usernames from large friend lists on Facebook, without being rate limited.
Home-page: https://github.com/narkopolo/fb_friend_list_scraper
Author: narkopolo
Author-email: narkopolo@riseup.net
License: GPL-3.0
Platform: UNKNOWN
Classifier: Development Status :: 2 - Pre-Alpha
Classifier: Topic :: System :: Installation/Setup
Classifier: Intended Audience :: Science/Research
Classifier: License :: OSI Approved :: GNU General Public License v3 (GPLv3)
Classifier: Operating System :: OS Independent
Classifier: Programming Language :: Python :: 3.6
Classifier: Programming Language :: Python :: 3.7
Classifier: Programming Language :: Python :: 3.8
Classifier: Programming Language :: Python :: 3.9
Classifier: Programming Language :: Python :: 3.10
Requires-Python: >=3.6
License-File: LICENSE
Requires-Dist: pyautogecko (==0.1.3)
Requires-Dist: beautifulsoup4 (==4.10.0)
Requires-Dist: selenium (==4.1.3)
Requires-Dist: tqdm (==4.43.0)
Requires-Dist: rich (==12.2.0)
Requires-Dist: selenium-wire (==4.6.3)
Requires-Dist: requests (==2.28.1)
